lazycodet/__init__.py
lazycodet/helper.py
lazycodet/nlp.py
lazycodet/variant.py
lazycodet/module/helper.py
lazycodet/module/nlp.py
lazycodet-0.0.47.dist-info/METADATA
lazycodet-0.0.47.dist-info/WHEEL
lazycodet-0.0.47.dist-info/top_level.txt
lazycodet-0.0.47.dist-info/RECORD
