Metadata-Version: 2.1
Name: lazycodet
Version: 0.0.47
Author: Nguyen Tan Tai
Author-email: nguyentantaitcag2000@gmail.com
Requires-Dist: unidecode
